{"startPage":"MainPage","pages":{"MainPage":{"layout":"DesktopLayout","assignments":[{"areaId":"AreaContent","contentId":"MainPageContent","type":"Content","backColor":"rgba(245, 245, 245, 1)"}]}},"layouts":{"DesktopLayout":{"areas":{"AreaHeader":{"height":100,"width":1600,"top":0,"left":0},"AreaContent":{"height":800,"width":1480,"top":100,"left":0},"AreaNavigation":{"height":800,"width":120,"top":100,"left":1480}},"width":1600,"height":900}},"contents":{"MainPageContent":{"path":"/contents/mappView/MainPageContent.html","height":800,"width":1480,"configurations":{}}},"configurations":{"activityCount":false}}